CMCCAPPLOG/GetNetWorkInfo.py
CMCCAPPLOG/LogUploader.py
CMCCAPPLOG/__init__.py
WZCMCCAPPLOG/GetNetWorkInfo.py
WZCMCCAPPLOG/LogUploader.py
WZCMCCAPPLOG/__init__.py
WZCMCCAPPLOGGER/GetNetWorkInfo.py
WZCMCCAPPLOGGER/LogUploader.py
WZCMCCAPPLOGGER/__init__.py
WZCMCCAPPLOGGER/__init__bak.py
WZCMCCAPPLOGGER-0.0.9.dist-info/LICENSE
WZCMCCAPPLOGGER-0.0.9.dist-info/METADATA
WZCMCCAPPLOGGER-0.0.9.dist-info/WHEEL
WZCMCCAPPLOGGER-0.0.9.dist-info/top_level.txt
WZCMCCAPPLOGGER-0.0.9.dist-info/RECORD
