Metadata-Version: 2.1
Name: WZCMCCAPPLOGGER
Version: 0.0.9
Summary: LOG
Home-page: https://github.com/pypa/sampleproject
Author: YHQ
Author-email: 228899059@qq.com
Classifier: Programming Language :: Python :: 3
Classifier: License :: OSI Approved :: MIT License
Classifier: Operating System :: OS Independent
License-File: LICENSE
